{"points": [], "tries": [{"player": "M.Nawaqanitawase", "team": "NSW", "p_anytime": 0.545, "exp_tries": 0.79}, {"player": "B.To'o", "team": "NSW", "p_anytime": 0.523, "exp_tries": 0.74}, {"player": "M.Nawaqanitawase", "team": "NSW", "p_anytime": 0.478, "exp_tries": 0.65}, {"player": "B.To'o", "team": "NSW", "p_anytime": 0.476, "exp_tries": 0.65}, {"player": "B.To'o", "team": "NSW", "p_anytime": 0.46, "exp_tries": 0.62}, {"player": "T.Koula", "team": "NSW", "p_anytime": 0.446, "exp_tries": 0.59}, {"player": "S.Cobbo", "team": "Queensland", "p_anytime": 0.445, "exp_tries": 0.59}, {"player": "M.Nawaqanitawase", "team": "NSW", "p_anytime": 0.44, "exp_tries": 0.58}, {"player": "S.Cobbo", "team": "Queensland", "p_anytime": 0.438, "exp_tries": 0.58}, {"player": "D.Lucas", "team": "NSW", "p_anytime": 0.41, "exp_tries": 0.53}, {"player": "D.Lucas", "team": "NSW", "p_anytime": 0.404, "exp_tries": 0.52}, {"player": "J.Tedesco", "team": "NSW", "p_anytime": 0.403, "exp_tries": 0.52}, {"player": "S.Cobbo", "team": "Queensland", "p_anytime": 0.373, "exp_tries": 0.47}, {"player": "K.Staggs", "team": "NSW", "p_anytime": 0.357, "exp_tries": 0.44}, {"player": "K.Staggs", "team": "NSW", "p_anytime": 0.35, "exp_tries": 0.43}, {"player": "H.Tabuai-Fidow", "team": "Queensland", "p_anytime": 0.347, "exp_tries": 0.43}, {"player": "H.Young", "team": "NSW", "p_anytime": 0.341, "exp_tries": 0.42}, {"player": "J.Fifita", "team": "Queensland", "p_anytime": 0.337, "exp_tries": 0.41}, {"player": "J.Fifita", "team": "Queensland", "p_anytime": 0.33, "exp_tries": 0.4}, {"player": "J.Tedesco", "team": "NSW", "p_anytime": 0.322, "exp_tries": 0.39}, {"player": "T.Koula", "team": "NSW", "p_anytime": 0.32, "exp_tries": 0.39}, {"player": "T.Koula", "team": "NSW", "p_anytime": 0.318, "exp_tries": 0.38}, {"player": "D.Lucas", "team": "NSW", "p_anytime": 0.31, "exp_tries": 0.37}, {"player": "R.Toia", "team": "Queensland", "p_anytime": 0.29, "exp_tries": 0.34}, {"player": "H.Tabuai-Fidow", "team": "Queensland", "p_anytime": 0.287, "exp_tries": 0.34}, {"player": "J.Fifita", "team": "Queensland", "p_anytime": 0.275, "exp_tries": 0.32}, {"player": "H.Young", "team": "NSW", "p_anytime": 0.273, "exp_tries": 0.32}, {"player": "J.Tedesco", "team": "NSW", "p_anytime": 0.271, "exp_tries": 0.32}, {"player": "M.Moses", "team": "NSW", "p_anytime": 0.263, "exp_tries": 0.3}, {"player": "K.Staggs", "team": "NSW", "p_anytime": 0.259, "exp_tries": 0.3}, {"player": "H.Young", "team": "NSW", "p_anytime": 0.247, "exp_tries": 0.28}, {"player": "H.Grant", "team": "Queensland", "p_anytime": 0.241, "exp_tries": 0.28}, {"player": "M.Moses", "team": "NSW", "p_anytime": 0.239, "exp_tries": 0.27}, {"player": "N.Cleary", "team": "NSW", "p_anytime": 0.234, "exp_tries": 0.27}, {"player": "S.Walker", "team": "Queensland", "p_anytime": 0.23, "exp_tries": 0.26}, {"player": "N.Cleary", "team": "NSW", "p_anytime": 0.229, "exp_tries": 0.26}, {"player": "H.Grant", "team": "Queensland", "p_anytime": 0.224, "exp_tries": 0.25}, {"player": "H.Grant", "team": "Queensland", "p_anytime": 0.217, "exp_tries": 0.24}, {"player": "B.Nikora", "team": "Queensland", "p_anytime": 0.216, "exp_tries": 0.24}, {"player": "H.Tabuai-Fidow", "team": "Queensland", "p_anytime": 0.215, "exp_tries": 0.24}, {"player": "K.Ponga", "team": "Queensland", "p_anytime": 0.211, "exp_tries": 0.24}, {"player": "N.Cleary", "team": "NSW", "p_anytime": 0.2, "exp_tries": 0.22}, {"player": "R.Toia", "team": "Queensland", "p_anytime": 0.199, "exp_tries": 0.22}, {"player": "C.Murray", "team": "NSW", "p_anytime": 0.187, "exp_tries": 0.21}, {"player": "K.Ponga", "team": "Queensland", "p_anytime": 0.186, "exp_tries": 0.21}, {"player": "K.Ponga", "team": "Queensland", "p_anytime": 0.182, "exp_tries": 0.2}, {"player": "S.Walker", "team": "Queensland", "p_anytime": 0.168, "exp_tries": 0.18}, {"player": "R.Toia", "team": "Queensland", "p_anytime": 0.167, "exp_tries": 0.18}, {"player": "C.Munster", "team": "Queensland", "p_anytime": 0.161, "exp_tries": 0.18}, {"player": "M.Moses", "team": "NSW", "p_anytime": 0.156, "exp_tries": 0.17}, {"player": "S.Walker", "team": "Queensland", "p_anytime": 0.151, "exp_tries": 0.16}, {"player": "E.Strange", "team": "NSW", "p_anytime": 0.151, "exp_tries": 0.16}, {"player": "B.Nikora", "team": "Queensland", "p_anytime": 0.144, "exp_tries": 0.16}, {"player": "E.Strange", "team": "NSW", "p_anytime": 0.144, "exp_tries": 0.16}, {"player": "A.Fonua-Blake", "team": "NSW", "p_anytime": 0.144, "exp_tries": 0.15}, {"player": "K.Capewell", "team": "Queensland", "p_anytime": 0.14, "exp_tries": 0.15}, {"player": "R.Robson", "team": "NSW", "p_anytime": 0.139, "exp_tries": 0.15}, {"player": "C.Murray", "team": "NSW", "p_anytime": 0.131, "exp_tries": 0.14}, {"player": "K.Finefeuiaki", "team": "Queensland", "p_anytime": 0.129, "exp_tries": 0.14}, {"player": "R.Robson", "team": "NSW", "p_anytime": 0.12, "exp_tries": 0.13}]}