{"id":"106840101","comp":"nrl","season":"2019","round":1,"home":"Melbourne Storm","away":"Brisbane Broncos","hs":22,"as":12,"date":"2019-03-14T19:50:00+11:00","venue":"AAMI Park","homeLineup":[{"pid":31881,"name":"Jahrome Hughes","pos":"Fullback","pts":4,"t":1,"g":0,"fg":0,"ta":0,"lb":1,"rm":227,"tk":2,"tb":2,"mt":2,"off":0,"err":0},{"pid":995805,"name":"Suliasi Vunivalu","pos":"Wing","pts":0,"t":0,"g":0,"fg":0,"ta":0,"lb":0,"rm":105,"tk":10,"tb":4,"mt":1,"off":2,"err":1},{"pid":30985,"name":"Will Chambers","pos":"Centre","pts":0,"t":0,"g":0,"fg":0,"ta":0,"lb":0,"rm":83,"tk":12,"tb":2,"mt":2,"off":0,"err":1},{"pid":1002004,"name":"Curtis Scott","pos":"Centre","pts":4,"t":1,"g":0,"fg":0,"ta":0,"lb":0,"rm":209,"tk":16,"tb":2,"mt":1,"off":0,"err":1},{"pid":995794,"name":"Josh Addo-Carr","pos":"Wing","pts":0,"t":0,"g":0,"fg":0,"ta":0,"lb":0,"rm":125,"tk":6,"tb":3,"mt":1,"off":2,"err":0},{"pid":995276,"name":"Cameron Munster","pos":"Five-Eighth","pts":0,"t":0,"g":0,"fg":0,"ta":2,"lb":0,"rm":76,"tk":18,"tb":3,"mt":2,"off":1,"err":0},{"pid":1003773,"name":"Brodie Croft","pos":"Halfback","pts":0,"t":0,"g":0,"fg":0,"ta":0,"lb":1,"rm":73,"tk":17,"tb":2,"mt":2,"off":0,"err":1},{"pid":31556,"name":"Jesse Bromwich","pos":"Prop","pts":4,"t":1,"g":0,"fg":0,"ta":0,"lb":1,"rm":156,"tk":23,"tb":1,"mt":2,"off":2,"err":1},{"pid":30665,"name":"Cameron Smith","pos":"Hooker","pts":6,"t":0,"g":3,"fg":0,"ta":0,"lb":0,"rm":56,"tk":49,"tb":1,"mt":2,"off":0,"err":0},{"pid":995921,"name":"Nelson Asofa-Solomona","pos":"Prop","pts":0,"t":0,"g":0,"fg":0,"ta":0,"lb":0,"rm":101,"tk":15,"tb":2,"mt":4,"off":2,"err":0},{"pid":31874,"name":"Felise Kaufusi","pos":"Second Row","pts":0,"t":0,"g":0,"fg":0,"ta":0,"lb":0,"rm":156,"tk":34,"tb":0,"mt":1,"off":0,"err":1},{"pid":31804,"name":"Kenny Bromwich","pos":"Second Row","pts":4,"t":1,"g":0,"fg":0,"ta":1,"lb":1,"rm":67,"tk":36,"tb":1,"mt":3,"off":0,"err":0},{"pid":31786,"name":"Dale Finucane","pos":"Lock","pts":0,"t":0,"g":0,"fg":0,"ta":0,"lb":0,"rm":94,"tk":32,"tb":2,"mt":1,"off":0,"err":1},{"pid":999917,"name":"Brandon Smith","pos":"Interchange","pts":0,"t":0,"g":0,"fg":0,"ta":0,"lb":0,"rm":141,"tk":20,"tb":4,"mt":0,"off":0,"err":1},{"pid":991474,"name":"Christian Welch","pos":"Interchange","pts":0,"t":0,"g":0,"fg":0,"ta":0,"lb":0,"rm":112,"tk":22,"tb":2,"mt":2,"off":2,"err":0},{"pid":991512,"name":"Tui Kamikamica","pos":"Interchange","pts":0,"t":0,"g":0,"fg":0,"ta":0,"lb":0,"rm":62,"tk":18,"tb":1,"mt":3,"off":0,"err":0},{"pid":31865,"name":"Tom Eisenhuth","pos":"Interchange","pts":0,"t":0,"g":0,"fg":0,"ta":0,"lb":0,"rm":19,"tk":4,"tb":1,"mt":0,"off":0,"err":0}],"awayLineup":[{"pid":31188,"name":"Darius Boyd","pos":"Fullback","pts":0,"t":0,"g":0,"fg":0,"ta":0,"lb":0,"rm":136,"tk":8,"tb":2,"mt":3,"off":1,"err":1},{"pid":31930,"name":"Corey Oates","pos":"Wing","pts":8,"t":2,"g":0,"fg":0,"ta":0,"lb":1,"rm":226,"tk":3,"tb":10,"mt":0,"off":0,"err":1},{"pid":31750,"name":"James Roberts","pos":"Centre","pts":0,"t":0,"g":0,"fg":0,"ta":0,"lb":0,"rm":0,"tk":2,"tb":0,"mt":0,"off":0,"err":0},{"pid":996003,"name":"Jack Bird","pos":"Centre","pts":0,"t":0,"g":0,"fg":0,"ta":1,"lb":0,"rm":128,"tk":15,"tb":5,"mt":2,"off":0,"err":1},{"pid":995889,"name":"Jamayne Isaako","pos":"Wing","pts":4,"t":0,"g":2,"fg":0,"ta":0,"lb":0,"rm":88,"tk":9,"tb":2,"mt":2,"off":1,"err":0},{"pid":991307,"name":"Anthony Milford","pos":"Five-Eighth","pts":0,"t":0,"g":0,"fg":0,"ta":0,"lb":0,"rm":48,"tk":23,"tb":0,"mt":3,"off":0,"err":0},{"pid":991256,"name":"Kodi Nikorima","pos":"Halfback","pts":0,"t":0,"g":0,"fg":0,"ta":0,"lb":0,"rm":83,"tk":22,"tb":1,"mt":8,"off":1,"err":0},{"pid":991459,"name":"Matt Lodge","pos":"Prop","pts":0,"t":0,"g":0,"fg":0,"ta":0,"lb":0,"rm":138,"tk":30,"tb":0,"mt":4,"off":1,"err":0},{"pid":31255,"name":"Andrew McCullough","pos":"Hooker","pts":0,"t":0,"g":0,"fg":0,"ta":0,"lb":0,"rm":44,"tk":50,"tb":0,"mt":3,"off":0,"err":0},{"pid":991253,"name":"Joe Ofahengaue","pos":"Prop","pts":0,"t":0,"g":0,"fg":0,"ta":0,"lb":0,"rm":107,"tk":26,"tb":2,"mt":1,"off":1,"err":1},{"pid":31423,"name":"Alex Glenn","pos":"Second Row","pts":0,"t":0,"g":0,"fg":0,"ta":0,"lb":0,"rm":68,"tk":37,"tb":1,"mt":3,"off":0,"err":0},{"pid":1000006,"name":"Jaydn Su'A","pos":"Second Row","pts":0,"t":0,"g":0,"fg":0,"ta":0,"lb":0,"rm":58,"tk":31,"tb":1,"mt":0,"off":0,"err":2},{"pid":31530,"name":"Matt Gillett","pos":"Lock","pts":0,"t":0,"g":0,"fg":0,"ta":0,"lb":0,"rm":44,"tk":59,"tb":0,"mt":1,"off":1,"err":0},{"pid":1012925,"name":"Kotoni Staggs","pos":"Interchange","pts":0,"t":0,"g":0,"fg":0,"ta":0,"lb":0,"rm":136,"tk":17,"tb":3,"mt":1,"off":0,"err":2},{"pid":1014350,"name":"David Fifita","pos":"Interchange","pts":0,"t":0,"g":0,"fg":0,"ta":0,"lb":0,"rm":82,"tk":18,"tb":0,"mt":0,"off":1,"err":0},{"pid":1014504,"name":"Tom Flegler","pos":"Interchange","pts":0,"t":0,"g":0,"fg":0,"ta":0,"lb":0,"rm":12,"tk":11,"tb":0,"mt":1,"off":0,"err":0},{"pid":995861,"name":"Tevita Pangai Junior","pos":"Interchange","pts":0,"t":0,"g":0,"fg":0,"ta":0,"lb":0,"rm":150,"tk":21,"tb":1,"mt":3,"off":3,"err":0}]}