{"id":"106841706","comp":"nrl","season":"2019","round":17,"home":"Sydney Roosters","away":"North Queensland Cowboys","hs":12,"as":15,"date":"2019-07-14T14:00:00+10:00","venue":"Central Coast Stadium","homeLineup":[{"pid":998505,"name":"Joseph Manu","pos":"Fullback","pts":0,"t":0,"g":0,"fg":0,"ta":0,"lb":0,"rm":207,"tk":2,"tb":1,"mt":1,"off":0,"err":2},{"pid":31867,"name":"Daniel Tupou","pos":"Wing","pts":0,"t":0,"g":0,"fg":0,"ta":0,"lb":0,"rm":161,"tk":4,"tb":2,"mt":2,"off":0,"err":1},{"pid":998416,"name":"Latrell Mitchell","pos":"Centre","pts":4,"t":0,"g":2,"fg":0,"ta":0,"lb":0,"rm":75,"tk":9,"tb":6,"mt":1,"off":1,"err":3},{"pid":31087,"name":"Brett Morris","pos":"Centre","pts":4,"t":1,"g":0,"fg":0,"ta":0,"lb":1,"rm":43,"tk":19,"tb":2,"mt":1,"off":1,"err":1},{"pid":31504,"name":"Ryan Hall","pos":"Wing","pts":0,"t":0,"g":0,"fg":0,"ta":0,"lb":0,"rm":189,"tk":4,"tb":8,"mt":0,"off":0,"err":0},{"pid":31911,"name":"Luke Keary","pos":"Five-Eighth","pts":0,"t":0,"g":0,"fg":0,"ta":0,"lb":1,"rm":110,"tk":22,"tb":4,"mt":4,"off":0,"err":1},{"pid":30914,"name":"Cooper Cronk","pos":"Halfback","pts":0,"t":0,"g":0,"fg":0,"ta":0,"lb":0,"rm":24,"tk":26,"tb":0,"mt":1,"off":0,"err":3},{"pid":31172,"name":"Jared Waerea-Hargreaves","pos":"Prop","pts":0,"t":0,"g":0,"fg":0,"ta":0,"lb":0,"rm":150,"tk":40,"tb":1,"mt":3,"off":1,"err":1},{"pid":31279,"name":"Jake Friend","pos":"Interchange","pts":4,"t":1,"g":0,"fg":0,"ta":0,"lb":1,"rm":21,"tk":49,"tb":3,"mt":3,"off":0,"err":1},{"pid":31835,"name":"Siosiua Taukeiaho","pos":"Prop","pts":0,"t":0,"g":0,"fg":0,"ta":0,"lb":0,"rm":64,"tk":22,"tb":0,"mt":0,"off":0,"err":0},{"pid":1000003,"name":"Nat Butcher","pos":"Second Row","pts":0,"t":0,"g":0,"fg":0,"ta":0,"lb":0,"rm":132,"tk":45,"tb":1,"mt":0,"off":0,"err":0},{"pid":30967,"name":"Mitchell Aubusson","pos":"Second Row","pts":0,"t":0,"g":0,"fg":0,"ta":1,"lb":0,"rm":71,"tk":52,"tb":1,"mt":1,"off":0,"err":0},{"pid":1007531,"name":"Victor Radley","pos":"Hooker","pts":0,"t":0,"g":0,"fg":0,"ta":0,"lb":0,"rm":53,"tk":51,"tb":0,"mt":5,"off":0,"err":1},{"pid":31846,"name":"Isaac Liu","pos":"Lock","pts":0,"t":0,"g":0,"fg":0,"ta":0,"lb":0,"rm":76,"tk":24,"tb":0,"mt":4,"off":0,"err":0},{"pid":999463,"name":"Angus Crichton","pos":"Interchange","pts":0,"t":0,"g":0,"fg":0,"ta":0,"lb":1,"rm":105,"tk":20,"tb":4,"mt":0,"off":0,"err":0},{"pid":1011034,"name":"Sitili Tupouniua","pos":"Interchange","pts":0,"t":0,"g":0,"fg":0,"ta":0,"lb":0,"rm":58,"tk":11,"tb":0,"mt":1,"off":0,"err":0},{"pid":998596,"name":"Poasa Faamausili","pos":"Interchange","pts":0,"t":0,"g":0,"fg":0,"ta":0,"lb":0,"rm":50,"tk":6,"tb":0,"mt":0,"off":1,"err":0}],"awayLineup":[{"pid":1007456,"name":"Scott Drinkwater","pos":"Fullback","pts":0,"t":0,"g":0,"fg":0,"ta":0,"lb":0,"rm":137,"tk":2,"tb":2,"mt":1,"off":1,"err":3},{"pid":31878,"name":"Kyle Feldt","pos":"Wing","pts":0,"t":0,"g":0,"fg":0,"ta":0,"lb":0,"rm":152,"tk":5,"tb":4,"mt":2,"off":0,"err":0},{"pid":31668,"name":"Jordan Kahu","pos":"Centre","pts":2,"t":0,"g":1,"fg":0,"ta":0,"lb":0,"rm":53,"tk":8,"tb":0,"mt":4,"off":0,"err":0},{"pid":991264,"name":"Tom Opacic","pos":"Centre","pts":0,"t":0,"g":0,"fg":0,"ta":0,"lb":0,"rm":92,"tk":10,"tb":4,"mt":2,"off":1,"err":0},{"pid":991357,"name":"Javid Bowen","pos":"Wing","pts":0,"t":0,"g":0,"fg":0,"ta":0,"lb":0,"rm":104,"tk":5,"tb":0,"mt":3,"off":1,"err":0},{"pid":1011014,"name":"Jake Clifford","pos":"Halfback","pts":9,"t":1,"g":2,"fg":1,"ta":0,"lb":1,"rm":65,"tk":10,"tb":4,"mt":1,"off":0,"err":1},{"pid":31430,"name":"Josh McGuire","pos":"Prop","pts":0,"t":0,"g":0,"fg":0,"ta":0,"lb":0,"rm":143,"tk":39,"tb":2,"mt":2,"off":0,"err":0},{"pid":31928,"name":"Jake Granville","pos":"Hooker","pts":0,"t":0,"g":0,"fg":0,"ta":1,"lb":0,"rm":50,"tk":48,"tb":0,"mt":2,"off":0,"err":0},{"pid":31799,"name":"Jordan McLean","pos":"Prop","pts":0,"t":0,"g":0,"fg":0,"ta":0,"lb":0,"rm":104,"tk":32,"tb":0,"mt":0,"off":0,"err":0},{"pid":31227,"name":"Gavin Cooper","pos":"Second Row","pts":0,"t":0,"g":0,"fg":0,"ta":0,"lb":0,"rm":104,"tk":32,"tb":1,"mt":3,"off":2,"err":0},{"pid":1003776,"name":"Shane Wright","pos":"Second Row","pts":0,"t":0,"g":0,"fg":0,"ta":0,"lb":0,"rm":99,"tk":45,"tb":0,"mt":3,"off":0,"err":1},{"pid":31768,"name":"Jason Taumalolo","pos":"Lock","pts":0,"t":0,"g":0,"fg":0,"ta":0,"lb":1,"rm":198,"tk":31,"tb":4,"mt":1,"off":0,"err":1},{"pid":991660,"name":"John Asiata","pos":"Five-Eighth","pts":4,"t":1,"g":0,"fg":0,"ta":1,"lb":1,"rm":41,"tk":19,"tb":2,"mt":2,"off":0,"err":0},{"pid":30946,"name":"Matthew Scott","pos":"Interchange","pts":0,"t":0,"g":0,"fg":0,"ta":0,"lb":0,"rm":79,"tk":21,"tb":0,"mt":3,"off":1,"err":0},{"pid":31217,"name":"Scott Bolton","pos":"Interchange","pts":0,"t":0,"g":0,"fg":0,"ta":0,"lb":0,"rm":50,"tk":15,"tb":0,"mt":4,"off":0,"err":0},{"pid":31932,"name":"Francis Molo","pos":"Interchange","pts":0,"t":0,"g":0,"fg":0,"ta":0,"lb":0,"rm":53,"tk":19,"tb":1,"mt":1,"off":1,"err":0},{"pid":995954,"name":"Coen Hess","pos":"Interchange","pts":0,"t":0,"g":0,"fg":0,"ta":0,"lb":0,"rm":69,"tk":6,"tb":1,"mt":0,"off":0,"err":0}]}