{"id":"106841702","comp":"nrl","season":"2019","round":17,"home":"Newcastle Knights","away":"Canterbury-Bankstown Bulldogs","hs":14,"as":20,"date":"2019-07-12T19:55:00+10:00","venue":"McDonald Jones Stadium","homeLineup":[{"pid":1000016,"name":"Connor Watson","pos":"Fullback","pts":0,"t":0,"g":0,"fg":0,"ta":0,"lb":0,"rm":197,"tk":8,"tb":15,"mt":1,"off":1,"err":0},{"pid":991379,"name":"Hymel Hunt","pos":"Wing","pts":0,"t":0,"g":0,"fg":0,"ta":0,"lb":0,"rm":135,"tk":2,"tb":0,"mt":1,"off":0,"err":0},{"pid":31888,"name":"Kurt Mann","pos":"Centre","pts":0,"t":0,"g":0,"fg":0,"ta":0,"lb":0,"rm":46,"tk":20,"tb":1,"mt":1,"off":0,"err":1},{"pid":997836,"name":"Jesse Ramien","pos":"Centre","pts":0,"t":0,"g":0,"fg":0,"ta":0,"lb":0,"rm":146,"tk":13,"tb":8,"mt":1,"off":1,"err":0},{"pid":31049,"name":"Shaun Kenny-Dowall","pos":"Wing","pts":8,"t":2,"g":0,"fg":0,"ta":0,"lb":1,"rm":157,"tk":5,"tb":9,"mt":1,"off":0,"err":1},{"pid":991687,"name":"Mason Lino","pos":"Five-Eighth","pts":6,"t":0,"g":3,"fg":0,"ta":0,"lb":0,"rm":42,"tk":17,"tb":1,"mt":1,"off":1,"err":1},{"pid":31111,"name":"Mitchell Pearce","pos":"Halfback","pts":0,"t":0,"g":0,"fg":0,"ta":1,"lb":0,"rm":55,"tk":12,"tb":1,"mt":5,"off":1,"err":1},{"pid":31794,"name":"James Gavet","pos":"Interchange","pts":0,"t":0,"g":0,"fg":0,"ta":0,"lb":0,"rm":63,"tk":22,"tb":1,"mt":1,"off":2,"err":0},{"pid":995944,"name":"Danny Levi","pos":"Hooker","pts":0,"t":0,"g":0,"fg":0,"ta":0,"lb":0,"rm":57,"tk":41,"tb":0,"mt":2,"off":0,"err":0},{"pid":996152,"name":"Josh King","pos":"Interchange","pts":0,"t":0,"g":0,"fg":0,"ta":0,"lb":0,"rm":48,"tk":19,"tb":0,"mt":2,"off":0,"err":0},{"pid":31612,"name":"Jamie Buhrer","pos":"Second Row","pts":0,"t":0,"g":0,"fg":0,"ta":0,"lb":0,"rm":52,"tk":44,"tb":1,"mt":1,"off":0,"err":2},{"pid":995942,"name":"Sione Mata'utia","pos":"Second Row","pts":0,"t":0,"g":0,"fg":0,"ta":0,"lb":0,"rm":90,"tk":37,"tb":2,"mt":3,"off":0,"err":1},{"pid":991280,"name":"Herman Ese'ese","pos":"Lock","pts":0,"t":0,"g":0,"fg":0,"ta":0,"lb":0,"rm":47,"tk":29,"tb":0,"mt":2,"off":0,"err":0},{"pid":31847,"name":"Tautau Moga","pos":"Interchange","pts":0,"t":0,"g":0,"fg":0,"ta":0,"lb":0,"rm":95,"tk":2,"tb":1,"mt":1,"off":0,"err":1},{"pid":31868,"name":"David Klemmer","pos":"Interchange","pts":0,"t":0,"g":0,"fg":0,"ta":0,"lb":0,"rm":147,"tk":26,"tb":4,"mt":0,"off":2,"err":1},{"pid":999904,"name":"Daniel Saifiti","pos":"Prop","pts":0,"t":0,"g":0,"fg":0,"ta":0,"lb":0,"rm":60,"tk":28,"tb":0,"mt":4,"off":2,"err":0},{"pid":31885,"name":"Tim Glasby","pos":"Prop","pts":0,"t":0,"g":0,"fg":0,"ta":0,"lb":0,"rm":83,"tk":31,"tb":2,"mt":1,"off":2,"err":0}],"awayLineup":[{"pid":991557,"name":"Dallin Watene-Zelezniak","pos":"Fullback","pts":0,"t":0,"g":0,"fg":0,"ta":0,"lb":0,"rm":203,"tk":0,"tb":6,"mt":0,"off":2,"err":1},{"pid":1007399,"name":"Nick Meaney","pos":"Wing","pts":8,"t":0,"g":4,"fg":0,"ta":0,"lb":0,"rm":73,"tk":5,"tb":2,"mt":4,"off":0,"err":1},{"pid":998057,"name":"Marcelo Montoya","pos":"Centre","pts":0,"t":0,"g":0,"fg":0,"ta":0,"lb":0,"rm":207,"tk":15,"tb":2,"mt":4,"off":0,"err":2},{"pid":31553,"name":"Will Hopoate","pos":"Centre","pts":4,"t":1,"g":0,"fg":0,"ta":0,"lb":1,"rm":208,"tk":20,"tb":2,"mt":2,"off":2,"err":3},{"pid":999929,"name":"Reimis Smith","pos":"Wing","pts":4,"t":1,"g":0,"fg":0,"ta":0,"lb":0,"rm":113,"tk":2,"tb":1,"mt":0,"off":2,"err":0},{"pid":1014513,"name":"Brandon Wakeham","pos":"Five-Eighth","pts":0,"t":0,"g":0,"fg":0,"ta":1,"lb":0,"rm":52,"tk":27,"tb":1,"mt":0,"off":0,"err":1},{"pid":998593,"name":"Jack Cogger","pos":"Halfback","pts":0,"t":0,"g":0,"fg":0,"ta":2,"lb":0,"rm":40,"tk":18,"tb":2,"mt":4,"off":1,"err":0},{"pid":31164,"name":"Aiden Tolman","pos":"Prop","pts":0,"t":0,"g":0,"fg":0,"ta":0,"lb":0,"rm":6,"tk":14,"tb":1,"mt":4,"off":0,"err":0},{"pid":991559,"name":"Michael Lichaa","pos":"Hooker","pts":0,"t":0,"g":0,"fg":0,"ta":0,"lb":0,"rm":86,"tk":50,"tb":0,"mt":1,"off":0,"err":0},{"pid":31924,"name":"Dylan Napa","pos":"Prop","pts":0,"t":0,"g":0,"fg":0,"ta":0,"lb":0,"rm":169,"tk":38,"tb":2,"mt":6,"off":0,"err":1},{"pid":31801,"name":"Josh Jackson","pos":"Second Row","pts":0,"t":0,"g":0,"fg":0,"ta":0,"lb":0,"rm":89,"tk":33,"tb":0,"mt":3,"off":2,"err":1},{"pid":996143,"name":"Corey Harawira-Naera","pos":"Second Row","pts":4,"t":1,"g":0,"fg":0,"ta":0,"lb":2,"rm":126,"tk":27,"tb":4,"mt":9,"off":2,"err":0},{"pid":991550,"name":"Chris Smith","pos":"Lock","pts":0,"t":0,"g":0,"fg":0,"ta":0,"lb":0,"rm":35,"tk":21,"tb":0,"mt":8,"off":0,"err":0},{"pid":991267,"name":"Adam Elliott","pos":"Interchange","pts":0,"t":0,"g":0,"fg":0,"ta":0,"lb":0,"rm":136,"tk":22,"tb":2,"mt":3,"off":1,"err":1},{"pid":995875,"name":"Renouf Atoni","pos":"Interchange","pts":0,"t":0,"g":0,"fg":0,"ta":0,"lb":0,"rm":87,"tk":19,"tb":1,"mt":0,"off":0,"err":0},{"pid":991720,"name":"Sauaso Sue","pos":"Interchange","pts":0,"t":0,"g":0,"fg":0,"ta":0,"lb":0,"rm":30,"tk":3,"tb":0,"mt":0,"off":0,"err":1},{"pid":996042,"name":"Jeremy Marshall-King","pos":"Interchange","pts":0,"t":0,"g":0,"fg":0,"ta":0,"lb":0,"rm":31,"tk":14,"tb":0,"mt":0,"off":0,"err":1}]}