{"id":"120670402","comp":"nrl","season":"2023","round":4,"home":"Melbourne Storm","away":"Wests Tigers","hs":24,"as":12,"date":"2023-03-24T18:00:00+11:00","venue":"AAMI Park","homeLineup":[{"pid":1007399,"name":"Nick Meaney","pos":"Fullback","pts":12,"t":1,"g":4,"fg":0,"ta":0,"lb":1,"rm":182,"tk":3,"tb":3,"mt":0,"off":0,"err":0},{"pid":1025395,"name":"William Warbrick","pos":"Wing","pts":4,"t":1,"g":0,"fg":0,"ta":0,"lb":2,"rm":171,"tk":4,"tb":3,"mt":2,"off":1,"err":2},{"pid":999929,"name":"Reimis Smith","pos":"Centre","pts":0,"t":0,"g":0,"fg":0,"ta":0,"lb":0,"rm":124,"tk":19,"tb":2,"mt":4,"off":1,"err":0},{"pid":1005771,"name":"Justin Olam","pos":"Centre","pts":4,"t":1,"g":0,"fg":0,"ta":0,"lb":0,"rm":122,"tk":0,"tb":4,"mt":1,"off":0,"err":1},{"pid":1018053,"name":"Xavier Coates","pos":"Wing","pts":0,"t":0,"g":0,"fg":0,"ta":1,"lb":0,"rm":101,"tk":3,"tb":1,"mt":0,"off":0,"err":0},{"pid":995276,"name":"Cameron Munster","pos":"Five-Eighth","pts":4,"t":1,"g":0,"fg":0,"ta":0,"lb":1,"rm":112,"tk":23,"tb":2,"mt":3,"off":1,"err":0},{"pid":991512,"name":"Tui Kamikamica","pos":"Prop","pts":0,"t":0,"g":0,"fg":0,"ta":0,"lb":0,"rm":78,"tk":31,"tb":2,"mt":1,"off":0,"err":0},{"pid":1011004,"name":"Harry Grant","pos":"Hooker","pts":0,"t":0,"g":0,"fg":0,"ta":0,"lb":0,"rm":43,"tk":49,"tb":0,"mt":6,"off":0,"err":0},{"pid":991474,"name":"Christian Welch","pos":"Prop","pts":0,"t":0,"g":0,"fg":0,"ta":0,"lb":0,"rm":120,"tk":39,"tb":3,"mt":2,"off":0,"err":1},{"pid":1021326,"name":"Trent Loiero","pos":"Second Row","pts":0,"t":0,"g":0,"fg":0,"ta":0,"lb":0,"rm":196,"tk":36,"tb":3,"mt":0,"off":0,"err":2},{"pid":1019602,"name":"Eliesa Katoa","pos":"Second Row","pts":0,"t":0,"g":0,"fg":0,"ta":2,"lb":1,"rm":127,"tk":28,"tb":5,"mt":2,"off":0,"err":2},{"pid":996152,"name":"Josh King","pos":"Lock","pts":0,"t":0,"g":0,"fg":0,"ta":0,"lb":0,"rm":155,"tk":39,"tb":1,"mt":3,"off":2,"err":0},{"pid":1025396,"name":"Tyran Wishart","pos":"Interchange","pts":0,"t":0,"g":0,"fg":0,"ta":0,"lb":0,"rm":18,"tk":7,"tb":0,"mt":0,"off":0,"err":0},{"pid":1026956,"name":"Alec MacDonald","pos":"Interchange","pts":0,"t":0,"g":0,"fg":0,"ta":0,"lb":0,"rm":74,"tk":18,"tb":3,"mt":2,"off":0,"err":0},{"pid":31535,"name":"Tariq Sims","pos":"Interchange","pts":0,"t":0,"g":0,"fg":0,"ta":0,"lb":0,"rm":70,"tk":7,"tb":0,"mt":1,"off":0,"err":0},{"pid":995994,"name":"Bronson Garlick","pos":"Interchange","pts":0,"t":0,"g":0,"fg":0,"ta":0,"lb":0,"rm":29,"tk":13,"tb":1,"mt":0,"off":1,"err":0},{"pid":31865,"name":"Tom Eisenhuth","pos":"Interchange","pts":0,"t":0,"g":0,"fg":0,"ta":0,"lb":0,"rm":0,"tk":0,"tb":0,"mt":0,"off":0,"err":0},{"pid":1025394,"name":"Jonah Pezet","pos":"Halfback","pts":0,"t":0,"g":0,"fg":0,"ta":0,"lb":0,"rm":25,"tk":30,"tb":1,"mt":3,"off":2,"err":1}],"awayLineup":[{"pid":1010603,"name":"Adam Doueihi","pos":"Fullback","pts":4,"t":0,"g":2,"fg":0,"ta":0,"lb":0,"rm":156,"tk":7,"tb":2,"mt":1,"off":3,"err":0},{"pid":1020463,"name":"Charlie Staines","pos":"Wing","pts":0,"t":0,"g":0,"fg":0,"ta":0,"lb":0,"rm":120,"tk":4,"tb":3,"mt":0,"off":0,"err":2},{"pid":995972,"name":"Brent Naden","pos":"Centre","pts":0,"t":0,"g":0,"fg":0,"ta":0,"lb":0,"rm":22,"tk":11,"tb":0,"mt":4,"off":1,"err":0},{"pid":1014567,"name":"Asu Kepaoa","pos":"Centre","pts":4,"t":1,"g":0,"fg":0,"ta":0,"lb":1,"rm":124,"tk":14,"tb":2,"mt":1,"off":0,"err":3},{"pid":1025408,"name":"Junior Tupou","pos":"Wing","pts":0,"t":0,"g":0,"fg":0,"ta":0,"lb":0,"rm":173,"tk":4,"tb":6,"mt":1,"off":0,"err":1},{"pid":1014513,"name":"Brandon Wakeham","pos":"Five-Eighth","pts":0,"t":0,"g":0,"fg":0,"ta":0,"lb":1,"rm":32,"tk":22,"tb":0,"mt":1,"off":0,"err":0},{"pid":991722,"name":"Luke Brooks","pos":"Halfback","pts":0,"t":0,"g":0,"fg":0,"ta":0,"lb":0,"rm":78,"tk":28,"tb":1,"mt":9,"off":2,"err":2},{"pid":1014529,"name":"Stefano Utoikamanu","pos":"Prop","pts":0,"t":0,"g":0,"fg":0,"ta":0,"lb":0,"rm":82,"tk":37,"tb":1,"mt":1,"off":0,"err":0},{"pid":31912,"name":"Api Koroisau","pos":"Hooker","pts":4,"t":1,"g":0,"fg":0,"ta":0,"lb":0,"rm":39,"tk":47,"tb":0,"mt":13,"off":1,"err":0},{"pid":31868,"name":"David Klemmer","pos":"Prop","pts":0,"t":0,"g":0,"fg":0,"ta":0,"lb":0,"rm":123,"tk":35,"tb":2,"mt":0,"off":1,"err":0},{"pid":1007443,"name":"Isaiah Papali'i","pos":"Second Row","pts":0,"t":0,"g":0,"fg":0,"ta":1,"lb":0,"rm":113,"tk":47,"tb":4,"mt":1,"off":1,"err":0},{"pid":995664,"name":"John Bateman","pos":"Second Row","pts":0,"t":0,"g":0,"fg":0,"ta":0,"lb":0,"rm":98,"tk":44,"tb":2,"mt":3,"off":3,"err":2},{"pid":1028578,"name":"Fonua Pole","pos":"Lock","pts":0,"t":0,"g":0,"fg":0,"ta":0,"lb":0,"rm":122,"tk":28,"tb":2,"mt":0,"off":0,"err":0},{"pid":1024045,"name":"Daine Laurie","pos":"Interchange","pts":0,"t":0,"g":0,"fg":0,"ta":0,"lb":0,"rm":18,"tk":1,"tb":1,"mt":0,"off":0,"err":0},{"pid":998433,"name":"Alex Twal","pos":"Interchange","pts":0,"t":0,"g":0,"fg":0,"ta":0,"lb":0,"rm":86,"tk":25,"tb":1,"mt":0,"off":0,"err":0},{"pid":1019564,"name":"Shawn Blore","pos":"Interchange","pts":0,"t":0,"g":0,"fg":0,"ta":0,"lb":0,"rm":29,"tk":24,"tb":0,"mt":0,"off":2,"err":0},{"pid":1019595,"name":"Alex Seyfarth","pos":"Interchange","pts":0,"t":0,"g":0,"fg":0,"ta":0,"lb":0,"rm":25,"tk":20,"tb":2,"mt":2,"off":0,"err":0},{"pid":1018534,"name":"Starford To'a","pos":"Interchange","pts":0,"t":0,"g":0,"fg":0,"ta":0,"lb":0,"rm":0,"tk":0,"tb":0,"mt":0,"off":0,"err":0}]}