{"id":"127550201","comp":"nrl","season":"2025","round":2,"home":"Newcastle Knights","away":"Dolphins","hs":26,"as":12,"date":"2025-03-13T20:00:00+11:00","venue":"McDonald Jones Stadium","homeLineup":[{"pid":999915,"name":"Kalyn Ponga","pos":"Fullback","pts":6,"t":0,"g":3,"fg":0,"ta":3,"lb":0,"rm":166,"tk":3,"tb":5,"mt":2,"off":2,"err":2},{"pid":1026948,"name":"James Schiller","pos":"Wing","pts":8,"t":2,"g":0,"fg":0,"ta":0,"lb":2,"rm":97,"tk":3,"tb":2,"mt":2,"off":0,"err":0},{"pid":31667,"name":"Dane Gagai","pos":"Centre","pts":4,"t":1,"g":0,"fg":0,"ta":0,"lb":1,"rm":100,"tk":25,"tb":4,"mt":5,"off":1,"err":0},{"pid":1018494,"name":"Bradman Best","pos":"Centre","pts":4,"t":1,"g":0,"fg":0,"ta":0,"lb":2,"rm":185,"tk":17,"tb":3,"mt":1,"off":1,"err":0},{"pid":1021754,"name":"Greg Marzhew","pos":"Wing","pts":0,"t":0,"g":0,"fg":0,"ta":0,"lb":0,"rm":180,"tk":4,"tb":10,"mt":0,"off":5,"err":3},{"pid":1035304,"name":"Fletcher Sharpe","pos":"Five-Eighth","pts":0,"t":0,"g":0,"fg":0,"ta":1,"lb":1,"rm":113,"tk":25,"tb":3,"mt":0,"off":3,"err":0},{"pid":998593,"name":"Jack Cogger","pos":"Halfback","pts":0,"t":0,"g":0,"fg":0,"ta":0,"lb":0,"rm":5,"tk":22,"tb":0,"mt":3,"off":0,"err":1},{"pid":999903,"name":"Jacob Saifiti","pos":"Prop","pts":0,"t":0,"g":0,"fg":0,"ta":0,"lb":0,"rm":84,"tk":10,"tb":0,"mt":2,"off":0,"err":0},{"pid":1014503,"name":"Phoenix Crossland","pos":"Hooker","pts":0,"t":0,"g":0,"fg":0,"ta":0,"lb":0,"rm":27,"tk":38,"tb":0,"mt":0,"off":0,"err":0},{"pid":1025374,"name":"Leo Thompson","pos":"Prop","pts":0,"t":0,"g":0,"fg":0,"ta":0,"lb":0,"rm":69,"tk":25,"tb":1,"mt":1,"off":0,"err":0},{"pid":1026953,"name":"Dylan Lucas","pos":"Second Row","pts":4,"t":1,"g":0,"fg":0,"ta":0,"lb":1,"rm":124,"tk":43,"tb":2,"mt":1,"off":0,"err":0},{"pid":1035305,"name":"Kai Pearce-Paul","pos":"Second Row","pts":0,"t":0,"g":0,"fg":0,"ta":1,"lb":0,"rm":56,"tk":37,"tb":0,"mt":6,"off":0,"err":2},{"pid":31756,"name":"Tyson Frizell","pos":"Lock","pts":0,"t":0,"g":0,"fg":0,"ta":0,"lb":0,"rm":102,"tk":24,"tb":1,"mt":1,"off":0,"err":3},{"pid":995886,"name":"Jayden Brailey","pos":"Interchange","pts":0,"t":0,"g":0,"fg":0,"ta":0,"lb":0,"rm":20,"tk":18,"tb":0,"mt":0,"off":0,"err":0},{"pid":1002007,"name":"Jack Hetherington","pos":"Interchange","pts":0,"t":0,"g":0,"fg":0,"ta":0,"lb":0,"rm":46,"tk":22,"tb":1,"mt":1,"off":0,"err":0},{"pid":991267,"name":"Adam Elliott","pos":"Interchange","pts":0,"t":0,"g":0,"fg":0,"ta":0,"lb":1,"rm":152,"tk":32,"tb":1,"mt":1,"off":1,"err":0},{"pid":1019560,"name":"Mat Croker","pos":"Interchange","pts":0,"t":0,"g":0,"fg":0,"ta":0,"lb":0,"rm":88,"tk":27,"tb":2,"mt":1,"off":0,"err":1},{"pid":1003182,"name":"Brodie Jones","pos":"Interchange","pts":0,"t":0,"g":0,"fg":0,"ta":0,"lb":0,"rm":0,"tk":0,"tb":0,"mt":0,"off":0,"err":0}],"awayLineup":[{"pid":1019546,"name":"Hamiso Tabuai-Fidow","pos":"Fullback","pts":0,"t":0,"g":0,"fg":0,"ta":0,"lb":0,"rm":102,"tk":6,"tb":2,"mt":0,"off":0,"err":0},{"pid":995889,"name":"Jamayne Isaako","pos":"Wing","pts":4,"t":0,"g":2,"fg":0,"ta":0,"lb":0,"rm":162,"tk":8,"tb":1,"mt":4,"off":0,"err":2},{"pid":1019540,"name":"Jake Averillo","pos":"Centre","pts":0,"t":0,"g":0,"fg":0,"ta":0,"lb":0,"rm":119,"tk":7,"tb":7,"mt":1,"off":2,"err":1},{"pid":1018095,"name":"Herbie Farnworth","pos":"Centre","pts":0,"t":0,"g":0,"fg":0,"ta":0,"lb":0,"rm":131,"tk":20,"tb":2,"mt":1,"off":6,"err":0},{"pid":1025408,"name":"Junior Tupou","pos":"Wing","pts":0,"t":0,"g":0,"fg":0,"ta":0,"lb":0,"rm":140,"tk":0,"tb":7,"mt":1,"off":0,"err":1},{"pid":991256,"name":"Kodi Nikorima","pos":"Five-Eighth","pts":0,"t":0,"g":0,"fg":0,"ta":0,"lb":0,"rm":79,"tk":10,"tb":0,"mt":2,"off":0,"err":1},{"pid":1030840,"name":"Isaiya Katoa","pos":"Halfback","pts":4,"t":1,"g":0,"fg":0,"ta":1,"lb":1,"rm":62,"tk":28,"tb":1,"mt":5,"off":1,"err":0},{"pid":999904,"name":"Daniel Saifiti","pos":"Prop","pts":0,"t":0,"g":0,"fg":0,"ta":0,"lb":0,"rm":101,"tk":30,"tb":2,"mt":2,"off":1,"err":1},{"pid":996042,"name":"Jeremy Marshall-King","pos":"Hooker","pts":0,"t":0,"g":0,"fg":0,"ta":0,"lb":0,"rm":32,"tk":44,"tb":1,"mt":3,"off":0,"err":2},{"pid":31874,"name":"Felise Kaufusi","pos":"Prop","pts":0,"t":0,"g":0,"fg":0,"ta":0,"lb":0,"rm":55,"tk":21,"tb":0,"mt":1,"off":0,"err":1},{"pid":1029924,"name":"Oryn Keeley","pos":"Second Row","pts":0,"t":0,"g":0,"fg":0,"ta":0,"lb":0,"rm":80,"tk":34,"tb":0,"mt":6,"off":0,"err":0},{"pid":1033441,"name":"Max Plath","pos":"Second Row","pts":0,"t":0,"g":0,"fg":0,"ta":0,"lb":0,"rm":89,"tk":28,"tb":1,"mt":3,"off":0,"err":0},{"pid":1014525,"name":"Tom Gilbert","pos":"Lock","pts":0,"t":0,"g":0,"fg":0,"ta":0,"lb":0,"rm":70,"tk":42,"tb":0,"mt":3,"off":0,"err":0},{"pid":1031178,"name":"Kurt Donoghoe","pos":"Interchange","pts":0,"t":0,"g":0,"fg":0,"ta":0,"lb":0,"rm":40,"tk":13,"tb":1,"mt":1,"off":0,"err":0},{"pid":999894,"name":"Josh Kerr","pos":"Interchange","pts":0,"t":0,"g":0,"fg":0,"ta":0,"lb":0,"rm":65,"tk":14,"tb":0,"mt":0,"off":1,"err":1},{"pid":31676,"name":"Mark Nicholls","pos":"Interchange","pts":4,"t":1,"g":0,"fg":0,"ta":0,"lb":1,"rm":43,"tk":26,"tb":1,"mt":1,"off":0,"err":0},{"pid":1002528,"name":"Ray Stone","pos":"Interchange","pts":0,"t":0,"g":0,"fg":0,"ta":0,"lb":0,"rm":40,"tk":33,"tb":0,"mt":3,"off":0,"err":0},{"pid":1011035,"name":"Sean O'Sullivan","pos":"Interchange","pts":0,"t":0,"g":0,"fg":0,"ta":0,"lb":0,"rm":0,"tk":0,"tb":0,"mt":0,"off":0,"err":0}]}