{"id":"98670501","comp":"nrl","season":"2016","round":5,"home":"Manly-Warringah Sea Eagles","away":"South Sydney Rabbitohs","hs":12,"as":16,"date":"2016-03-31T20:05:01+11:00","venue":"Brookvale Oval","homeLineup":[{"pid":30855,"name":"Brett Stewart","pos":"Fullback","pts":0,"t":0,"g":0,"fg":0,"ta":0,"lb":0,"rm":89,"tk":4,"tb":0,"mt":4,"off":1,"err":1},{"pid":31800,"name":"Jorge Taufua","pos":"Wing","pts":0,"t":0,"g":0,"fg":0,"ta":0,"lb":1,"rm":240,"tk":4,"tb":2,"mt":0,"off":0,"err":1},{"pid":30191,"name":"Jamie Lyon","pos":"Centre","pts":4,"t":0,"g":2,"fg":0,"ta":0,"lb":0,"rm":40,"tk":13,"tb":1,"mt":1,"off":1,"err":1},{"pid":31071,"name":"Steve Matai","pos":"Centre","pts":0,"t":0,"g":0,"fg":0,"ta":0,"lb":0,"rm":136,"tk":7,"tb":2,"mt":3,"off":1,"err":1},{"pid":995915,"name":"Tom Trbojevic","pos":"Wing","pts":0,"t":0,"g":0,"fg":0,"ta":0,"lb":1,"rm":218,"tk":4,"tb":3,"mt":0,"off":1,"err":1},{"pid":990750,"name":"Dylan Walker","pos":"Five-Eighth","pts":4,"t":1,"g":0,"fg":0,"ta":0,"lb":1,"rm":127,"tk":8,"tb":5,"mt":1,"off":0,"err":0},{"pid":31912,"name":"Api Koroisau","pos":"Halfback","pts":4,"t":1,"g":0,"fg":0,"ta":0,"lb":2,"rm":155,"tk":25,"tb":7,"mt":4,"off":0,"err":1},{"pid":31091,"name":"Nate Myles","pos":"Prop","pts":0,"t":0,"g":0,"fg":0,"ta":0,"lb":0,"rm":100,"tk":38,"tb":1,"mt":3,"off":0,"err":0},{"pid":999247,"name":"Matt Parcell","pos":"Hooker","pts":0,"t":0,"g":0,"fg":0,"ta":2,"lb":0,"rm":46,"tk":42,"tb":0,"mt":1,"off":1,"err":1},{"pid":31723,"name":"Brenton Lawrence","pos":"Prop","pts":0,"t":0,"g":0,"fg":0,"ta":0,"lb":0,"rm":115,"tk":29,"tb":0,"mt":4,"off":0,"err":0},{"pid":31613,"name":"Martin Taupau","pos":"Second Row","pts":0,"t":0,"g":0,"fg":0,"ta":0,"lb":0,"rm":96,"tk":19,"tb":2,"mt":1,"off":2,"err":1},{"pid":30931,"name":"Feleti Mateo","pos":"Second Row","pts":0,"t":0,"g":0,"fg":0,"ta":0,"lb":0,"rm":103,"tk":19,"tb":1,"mt":4,"off":0,"err":2},{"pid":31452,"name":"Lewis Brown","pos":"Interchange","pts":0,"t":0,"g":0,"fg":0,"ta":0,"lb":0,"rm":86,"tk":5,"tb":0,"mt":0,"off":1,"err":0},{"pid":31852,"name":"Josh Starling","pos":"Interchange","pts":0,"t":0,"g":0,"fg":0,"ta":0,"lb":0,"rm":150,"tk":26,"tb":0,"mt":1,"off":0,"err":0},{"pid":31554,"name":"Darcy Lussick","pos":"Lock","pts":0,"t":0,"g":0,"fg":0,"ta":0,"lb":0,"rm":88,"tk":22,"tb":0,"mt":1,"off":0,"err":0},{"pid":31606,"name":"Siosaia Vave","pos":"Interchange","pts":0,"t":0,"g":0,"fg":0,"ta":0,"lb":0,"rm":186,"tk":20,"tb":0,"mt":0,"off":2,"err":0},{"pid":31691,"name":"Blake Leary","pos":"Interchange","pts":0,"t":0,"g":0,"fg":0,"ta":0,"lb":0,"rm":35,"tk":10,"tb":0,"mt":0,"off":1,"err":0}],"awayLineup":[{"pid":31036,"name":"Greg Inglis","pos":"Fullback","pts":0,"t":0,"g":0,"fg":0,"ta":0,"lb":1,"rm":110,"tk":9,"tb":3,"mt":2,"off":0,"err":1},{"pid":31886,"name":"Kirisome Auva'a","pos":"Wing","pts":0,"t":0,"g":0,"fg":0,"ta":0,"lb":0,"rm":82,"tk":9,"tb":1,"mt":2,"off":0,"err":0},{"pid":991379,"name":"Hymel Hunt","pos":"Centre","pts":0,"t":0,"g":0,"fg":0,"ta":0,"lb":0,"rm":155,"tk":15,"tb":4,"mt":1,"off":1,"err":0},{"pid":991596,"name":"Aaron Gray","pos":"Wing","pts":0,"t":0,"g":0,"fg":0,"ta":0,"lb":0,"rm":89,"tk":1,"tb":2,"mt":0,"off":0,"err":1},{"pid":995278,"name":"Cody Walker","pos":"Five-Eighth","pts":8,"t":1,"g":2,"fg":0,"ta":0,"lb":1,"rm":50,"tk":19,"tb":1,"mt":4,"off":0,"err":0},{"pid":31911,"name":"Luke Keary","pos":"Halfback","pts":0,"t":0,"g":0,"fg":0,"ta":0,"lb":0,"rm":41,"tk":26,"tb":2,"mt":2,"off":0,"err":1},{"pid":31704,"name":"George Burgess","pos":"Prop","pts":0,"t":0,"g":0,"fg":0,"ta":0,"lb":0,"rm":76,"tk":25,"tb":2,"mt":1,"off":0,"err":0},{"pid":991606,"name":"Cameron McInnes","pos":"Hooker","pts":8,"t":2,"g":0,"fg":0,"ta":1,"lb":2,"rm":37,"tk":46,"tb":2,"mt":1,"off":0,"err":0},{"pid":31499,"name":"Sam Burgess","pos":"Prop","pts":0,"t":0,"g":0,"fg":0,"ta":0,"lb":0,"rm":148,"tk":29,"tb":2,"mt":3,"off":0,"err":1},{"pid":31873,"name":"Chris Grevsmuhl","pos":"Second Row","pts":0,"t":0,"g":0,"fg":0,"ta":0,"lb":1,"rm":133,"tk":23,"tb":3,"mt":2,"off":0,"err":1},{"pid":990973,"name":"Kyle Turner","pos":"Second Row","pts":0,"t":0,"g":0,"fg":0,"ta":0,"lb":0,"rm":93,"tk":33,"tb":0,"mt":1,"off":0,"err":0},{"pid":1001235,"name":"Nathan Brown","pos":"Lock","pts":0,"t":0,"g":0,"fg":0,"ta":0,"lb":0,"rm":114,"tk":29,"tb":0,"mt":1,"off":2,"err":0},{"pid":31917,"name":"Damien Cook","pos":"Interchange","pts":0,"t":0,"g":0,"fg":0,"ta":0,"lb":0,"rm":0,"tk":17,"tb":0,"mt":1,"off":0,"err":0},{"pid":31492,"name":"Jason Clark","pos":"Interchange","pts":0,"t":0,"g":0,"fg":0,"ta":0,"lb":0,"rm":53,"tk":34,"tb":0,"mt":1,"off":0,"err":0},{"pid":31477,"name":"Dave Tyrrell","pos":"Interchange","pts":0,"t":0,"g":0,"fg":0,"ta":0,"lb":0,"rm":42,"tk":19,"tb":0,"mt":1,"off":0,"err":0},{"pid":31915,"name":"Tom Burgess","pos":"Interchange","pts":0,"t":0,"g":0,"fg":0,"ta":0,"lb":0,"rm":77,"tk":12,"tb":0,"mt":3,"off":0,"err":0},{"pid":31629,"name":"Michael Oldfield","pos":"Centre","pts":0,"t":0,"g":0,"fg":0,"ta":0,"lb":0,"rm":86,"tk":13,"tb":0,"mt":0,"off":0,"err":1}]}