{"id":"98670203","comp":"nrl","season":"2016","round":2,"home":"Canberra Raiders","away":"Sydney Roosters","hs":21,"as":20,"date":"2016-03-12T15:00:03+11:00","venue":"GIO Stadium","homeLineup":[{"pid":31793,"name":"Jack Wighton","pos":"Fullback","pts":0,"t":0,"g":0,"fg":0,"ta":2,"lb":0,"rm":115,"tk":4,"tb":1,"mt":2,"off":0,"err":2},{"pid":31854,"name":"Edrick Lee","pos":"Wing","pts":0,"t":0,"g":0,"fg":0,"ta":0,"lb":0,"rm":68,"tk":1,"tb":0,"mt":0,"off":0,"err":2},{"pid":31448,"name":"Jarrod Croker","pos":"Centre","pts":8,"t":1,"g":2,"fg":0,"ta":1,"lb":1,"rm":60,"tk":12,"tb":1,"mt":1,"off":1,"err":3},{"pid":31590,"name":"Joey Leilua","pos":"Centre","pts":0,"t":0,"g":0,"fg":0,"ta":0,"lb":0,"rm":118,"tk":7,"tb":3,"mt":0,"off":2,"err":1},{"pid":31284,"name":"Jordan Rapana","pos":"Wing","pts":0,"t":0,"g":0,"fg":0,"ta":0,"lb":1,"rm":139,"tk":3,"tb":3,"mt":0,"off":0,"err":3},{"pid":997798,"name":"Lachlan Croker","pos":"Five-Eighth","pts":0,"t":0,"g":0,"fg":0,"ta":0,"lb":0,"rm":27,"tk":7,"tb":0,"mt":2,"off":0,"err":1},{"pid":31731,"name":"Sam Williams","pos":"Halfback","pts":1,"t":0,"g":0,"fg":1,"ta":0,"lb":0,"rm":20,"tk":10,"tb":0,"mt":3,"off":1,"err":1},{"pid":31833,"name":"Shannon Boyd","pos":"Prop","pts":0,"t":0,"g":0,"fg":0,"ta":0,"lb":0,"rm":55,"tk":30,"tb":0,"mt":1,"off":0,"err":0},{"pid":999039,"name":"Josh Hodgson","pos":"Hooker","pts":0,"t":0,"g":0,"fg":0,"ta":0,"lb":1,"rm":31,"tk":28,"tb":1,"mt":3,"off":0,"err":1},{"pid":31098,"name":"Frank-Paul Nu'uausala","pos":"Prop","pts":0,"t":0,"g":0,"fg":0,"ta":0,"lb":0,"rm":49,"tk":22,"tb":0,"mt":0,"off":0,"err":0},{"pid":31677,"name":"Josh Papali'i","pos":"Second Row","pts":8,"t":2,"g":0,"fg":0,"ta":0,"lb":1,"rm":86,"tk":22,"tb":2,"mt":1,"off":4,"err":1},{"pid":999043,"name":"Elliott Whitehead","pos":"Second Row","pts":0,"t":0,"g":0,"fg":0,"ta":0,"lb":0,"rm":67,"tk":34,"tb":0,"mt":1,"off":1,"err":1},{"pid":31456,"name":"Shaun Fensom","pos":"Lock","pts":0,"t":0,"g":0,"fg":0,"ta":0,"lb":0,"rm":0,"tk":1,"tb":0,"mt":1,"off":0,"err":0},{"pid":31526,"name":"Kurt Baptiste","pos":"Interchange","pts":0,"t":0,"g":0,"fg":0,"ta":1,"lb":0,"rm":16,"tk":15,"tb":0,"mt":2,"off":0,"err":0},{"pid":31146,"name":"Iosia Soliola","pos":"Interchange","pts":4,"t":1,"g":0,"fg":0,"ta":0,"lb":1,"rm":154,"tk":41,"tb":1,"mt":1,"off":1,"err":1},{"pid":31823,"name":"Paul Vaughan","pos":"Interchange","pts":0,"t":0,"g":0,"fg":0,"ta":0,"lb":0,"rm":174,"tk":19,"tb":4,"mt":1,"off":0,"err":0},{"pid":30910,"name":"Jeff Lima","pos":"Interchange","pts":0,"t":0,"g":0,"fg":0,"ta":0,"lb":0,"rm":161,"tk":28,"tb":0,"mt":1,"off":0,"err":0}],"awayLineup":[{"pid":31442,"name":"Blake Ferguson","pos":"Centre","pts":4,"t":1,"g":0,"fg":0,"ta":0,"lb":0,"rm":131,"tk":13,"tb":1,"mt":2,"off":0,"err":0},{"pid":31867,"name":"Daniel Tupou","pos":"Wing","pts":0,"t":0,"g":0,"fg":0,"ta":0,"lb":0,"rm":83,"tk":2,"tb":1,"mt":1,"off":0,"err":0},{"pid":31468,"name":"Dale Copley","pos":"Centre","pts":0,"t":0,"g":0,"fg":0,"ta":0,"lb":0,"rm":70,"tk":7,"tb":0,"mt":1,"off":0,"err":1},{"pid":31049,"name":"Shaun Kenny-Dowall","pos":"Wing","pts":0,"t":0,"g":0,"fg":0,"ta":1,"lb":0,"rm":89,"tk":1,"tb":0,"mt":3,"off":0,"err":0},{"pid":998416,"name":"Latrell Mitchell","pos":"Fullback","pts":8,"t":1,"g":2,"fg":0,"ta":0,"lb":1,"rm":143,"tk":2,"tb":5,"mt":1,"off":0,"err":2},{"pid":995856,"name":"Jayden Nikorima","pos":"Five-Eighth","pts":4,"t":1,"g":0,"fg":0,"ta":0,"lb":1,"rm":92,"tk":13,"tb":1,"mt":5,"off":0,"err":1},{"pid":995281,"name":"Jackson Hastings","pos":"Halfback","pts":0,"t":0,"g":0,"fg":0,"ta":1,"lb":0,"rm":37,"tk":21,"tb":1,"mt":0,"off":0,"err":2},{"pid":31803,"name":"Kane Evans","pos":"Prop","pts":0,"t":0,"g":0,"fg":0,"ta":0,"lb":0,"rm":128,"tk":16,"tb":0,"mt":1,"off":1,"err":0},{"pid":31279,"name":"Jake Friend","pos":"Hooker","pts":0,"t":0,"g":0,"fg":0,"ta":1,"lb":0,"rm":30,"tk":47,"tb":1,"mt":1,"off":1,"err":0},{"pid":31924,"name":"Dylan Napa","pos":"Prop","pts":0,"t":0,"g":0,"fg":0,"ta":0,"lb":0,"rm":196,"tk":15,"tb":2,"mt":1,"off":0,"err":1},{"pid":31021,"name":"Aidan Guerra","pos":"Second Row","pts":4,"t":1,"g":0,"fg":0,"ta":0,"lb":0,"rm":97,"tk":27,"tb":3,"mt":3,"off":2,"err":0},{"pid":30967,"name":"Mitchell Aubusson","pos":"Second Row","pts":0,"t":0,"g":0,"fg":0,"ta":0,"lb":1,"rm":128,"tk":20,"tb":1,"mt":0,"off":1,"err":1},{"pid":31846,"name":"Isaac Liu","pos":"Interchange","pts":0,"t":0,"g":0,"fg":0,"ta":0,"lb":0,"rm":99,"tk":15,"tb":1,"mt":2,"off":0,"err":0},{"pid":31835,"name":"Siosiua Taukeiaho","pos":"Lock","pts":0,"t":0,"g":0,"fg":0,"ta":1,"lb":0,"rm":170,"tk":27,"tb":1,"mt":0,"off":0,"err":0},{"pid":31249,"name":"Sam Moa","pos":"Interchange","pts":0,"t":0,"g":0,"fg":0,"ta":0,"lb":0,"rm":138,"tk":16,"tb":1,"mt":0,"off":0,"err":0},{"pid":30785,"name":"Ian Henderson","pos":"Interchange","pts":0,"t":0,"g":0,"fg":0,"ta":0,"lb":0,"rm":0,"tk":0,"tb":0,"mt":0,"off":0,"err":0},{"pid":996073,"name":"Vincent Leuluai","pos":"Interchange","pts":0,"t":0,"g":0,"fg":0,"ta":0,"lb":0,"rm":32,"tk":0,"tb":0,"mt":0,"off":0,"err":0}]}